anji_orm/__init__.py
anji_orm/core/__init__.py
anji_orm/core/context.py
anji_orm/core/executor.py
anji_orm/core/indexes.py
anji_orm/core/loggers.py
anji_orm/core/model.py
anji_orm/core/utils.py
anji_orm/core/ast/__init__.py
anji_orm/core/ast/base.py
anji_orm/core/ast/filters.py
anji_orm/core/ast/operations.py
anji_orm/core/ast/rows.py
anji_orm/core/ast/transformation.py
anji_orm/core/ast/utils.py
anji_orm/core/fields/__init__.py
anji_orm/core/fields/base.py
anji_orm/core/fields/extras.py
anji_orm/core/fields/relation.py
anji_orm/core/parser/__init__.py
anji_orm/core/parser/base.py
anji_orm/core/parser/filter_parser.py
anji_orm/core/parser/operation_parser.py
anji_orm/core/parser/transformation_parser.py
anji_orm/core/register/__init__.py
anji_orm/core/register/adapter.py
anji_orm/core/register/base.py
anji_orm/core/tools/__init__.py
anji_orm/core/tools/json.py
anji_orm/couchdb/__init__.py
anji_orm/couchdb/executor.py
anji_orm/couchdb/register.py
anji_orm/couchdb/utils.py
anji_orm/couchdb/lib/__init__.py
anji_orm/couchdb/lib/base.py
anji_orm/couchdb/lib/design.py
anji_orm/couchdb/lib/function.py
anji_orm/couchdb/parser/__init__.py
anji_orm/couchdb/parser/filter_parser.py
anji_orm/couchdb/parser/operation_parser.py
anji_orm/couchdb/parser/transformation_parser.py
anji_orm/extensions/__init__.py
anji_orm/extensions/exceptions.py
anji_orm/extensions/files/__init__.py
anji_orm/extensions/files/couchdb.py
anji_orm/extensions/files/disk.py
anji_orm/extensions/files/minio.py
anji_orm/extensions/files/base/__init__.py
anji_orm/extensions/files/base/core.py
anji_orm/extensions/files/base/data_model.py
anji_orm/extensions/files/base/fields.py
anji_orm/extras/__init__.py
anji_orm/extras/verbose.py
anji_orm/rethinkdb/__init__.py
anji_orm/rethinkdb/executor.py
anji_orm/rethinkdb/register.py
anji_orm/rethinkdb/utils.py
anji_orm/rethinkdb/parser/__init__.py
anji_orm/rethinkdb/parser/filter_parser.py
anji_orm/rethinkdb/parser/operation_parser.py
anji_orm-0.11.7.dist-info/LICENSE.txt
anji_orm-0.11.7.dist-info/METADATA
anji_orm-0.11.7.dist-info/WHEEL
anji_orm-0.11.7.dist-info/top_level.txt
anji_orm-0.11.7.dist-info/RECORD
