Metadata-Version: 2.1
Name: anji-orm
Version: 0.11.7
Summary: RethinkDB based ORM
Home-page: https://gitlab.com/AnjiProject/anji-orm
Author: Bogdan Gladyshev
Author-email: siredvin.dark@gmail.com
License: MIT license
Keywords: rethinkdb asyncio orm
Platform: UNKNOWN
Classifier: Development Status :: 5 - Production/Stable
Classifier: Intended Audience :: Developers
Classifier: License :: OSI Approved :: MIT License
Classifier: Natural Language :: English
Classifier: Programming Language :: Python :: 3.5
Classifier: Programming Language :: Python :: 3.6
Classifier: Programming Language :: Python :: 3.7
Classifier: Framework :: AsyncIO
Requires-Dist: humanize (~=0.5.1)
Requires-Dist: lazy (~=1.3)
Requires-Dist: jsonschema (>=2.6.0)
Requires-Dist: aenum (~=2.1.2)
Requires-Dist: toolz (~=0.9.0)
Requires-Dist: funcsubs (>=0.4.0)
Provides-Extra: all
Requires-Dist: repool-forked (>=1.0.0) ; extra == 'all'
Requires-Dist: async-repool (>=1.0.0) ; extra == 'all'
Requires-Dist: aiohttp (<4,>=3.2.1) ; extra == 'all'
Requires-Dist: requests (<=2.21.0) ; extra == 'all'
Requires-Dist: sseclient-py (~=1.7) ; extra == 'all'
Requires-Dist: unqlite (~=0.7.1) ; extra == 'all'
Requires-Dist: aiofiles (~=0.4.0) ; extra == 'all'
Requires-Dist: minio (>=5.0.7) ; extra == 'all'
Provides-Extra: couchdb-async
Requires-Dist: aiohttp (<4,>=3.2.1) ; extra == 'couchdb-async'
Provides-Extra: couchdb-sync
Requires-Dist: requests (<=2.21.0) ; extra == 'couchdb-sync'
Requires-Dist: sseclient-py (~=1.7) ; extra == 'couchdb-sync'
Provides-Extra: file-disk
Requires-Dist: aiofiles (~=0.4.0) ; extra == 'file-disk'
Provides-Extra: minio-async
Requires-Dist: minio (>=5.0.7) ; extra == 'minio-async'
Requires-Dist: aiohttp (<4,>=3.2.1) ; extra == 'minio-async'
Provides-Extra: minio-sync
Requires-Dist: minio (>=5.0.7) ; extra == 'minio-sync'
Provides-Extra: rethinkdb-async
Requires-Dist: async-repool (>=1.0.0) ; extra == 'rethinkdb-async'
Provides-Extra: rethinkdb-sync
Requires-Dist: repool-forked (>=1.0.0) ; extra == 'rethinkdb-sync'
Provides-Extra: unqlite
Requires-Dist: unqlite (~=0.7.1) ; extra == 'unqlite'
